{
  "project_info": {
    "project_number": "227599926991",
    "firebase_url": "https://cut-smartbanking-app-default-rtdb.firebaseio.com",
    "project_id": "cut-smartbanking-app",
    "storage_bucket": "cut-smartbanking-app.appspot.com"
  },
  "client": [
    {
      "client_info": {
        "mobilesdk_app_id": "1:227599926991:android:9e1018e786db74b390d9ba",
        "android_client_info": {
          "package_name": "com.example.bloem_travel_app"
        }
      },
      "oauth_client": [],
      "api_key": [
        {
          "current_key": "AIzaSyB5yDlF-4sGO4c1B9i4mz2FSHUbuDed8mo"
        }
      ],
      "services": {
        "appinvite_service": {
          "other_platform_oauth_client": []
        }
      }
    },
    {
      "client_info": {
        "mobilesdk_app_id": "1:227599926991:android:46bf38e5fc3a236890d9ba",
        "android_client_info": {
          "package_name": "com.example.cut_smartbanking_app"
        }
      },
      "oauth_client": [],
      "api_key": [
        {
          "current_key": "AIzaSyB5yDlF-4sGO4c1B9i4mz2FSHUbuDed8mo"
        }
      ],
      "services": {
        "appinvite_service": {
          "other_platform_oauth_client": []
        }
      }
    },
    {
      "client_info": {
        "mobilesdk_app_id": "1:227599926991:android:5b651e6c974c9c7390d9ba",
        "android_client_info": {
          "package_name": "com.example.transport_app"
        }
      },
      "oauth_client": [],
      "api_key": [
        {
          "current_key": "AIzaSyB5yDlF-4sGO4c1B9i4mz2FSHUbuDed8mo"
        }
      ],
      "services": {
        "appinvite_service": {
          "other_platform_oauth_client": []
        }
      }
    }
  ],
  "configuration_version": "1"
}